Workbook
Name UPDATE: '[1]Data Sheet'!$E$1

Sheet raw data
A1: ='[1]Data Sheet'!B1 -> TATA CONSULTANCY SERVICES LTD
A3: Narration | B3: 43891 | C3: ='[1]Data Sheet'!F16 -> 44286 | D3: ='[1]Data Sheet'!G16 -> 44651 | E3: ='[1]Data Sheet'!H16 -> 45016 | F3: ='[1]Data Sheet'!I16 -> 45382 | G3: ='[1]Data Sheet'!J16 -> 45747
A4: Sales | B4: ='[1]Data Sheet'!E17 -> 156949 | C4: ='[1]Data Sheet'!F17 -> 164177 | D4: ='[1]Data Sheet'!G17 -> 191754 | E4: ='[1]Data Sheet'!H17 -> 225458 | F4: ='[1]Data Sheet'!I17 -> 240893 | G4: ='[1]Data Sheet'!J17 -> 255324
A5: Expenses | B5: =SUM('[1]Data Sheet'!E18,'[1]Data Sheet'!E20:E24, -1*'[1]Data Sheet'!E19) -> 114840 | C5: =SUM('[1]Data Sheet'!F18,'[1]Data Sheet'!F20:F24, -1*'[1]Data Sheet'!F19) -> 117631 | D5: =SUM('[1]Data Sheet'!G18,'[1]Data Sheet'!G20:G24, -1*'[1]Data Sheet'!G19) -> 138697 | E5: =SUM('[1]Data Sheet'!H18,'[1]Data Sheet'!H20:H24, -1*'[1]Data Sheet'!H19) -> 166199 | F5: =SUM('[1]Data Sheet'!I18,'[1]Data Sheet'!I20:I24, -1*'[1]Data Sheet'!I19) -> 176597 | G5: =SUM('[1]Data Sheet'!J18,'[1]Data Sheet'!J20:J24, -1*'[1]Data Sheet'!J19) -> 187917
A6: Operating Profit | B6: =B4-B5 -> 42109 | C6: =C4-C5 -> 46546 | D6: =D4-D5 -> 53057 | E6: =E4-E5 -> 59259 | F6: =F4-F5 -> 64296 | G6: =G4-G5 -> 67407
A7: Other Income | B7: ='[1]Data Sheet'!E25 -> 4592 | C7: ='[1]Data Sheet'!F25 -> 1916 | D7: ='[1]Data Sheet'!G25 -> 4018 | E7: ='[1]Data Sheet'!H25 -> 3449 | F7: ='[1]Data Sheet'!I25 -> 3464 | G7: ='[1]Data Sheet'!J25 -> 3962
A8: Depreciation | B8: ='[1]Data Sheet'!E26 -> 3529 | C8: ='[1]Data Sheet'!F26 -> 4065 | D8: ='[1]Data Sheet'!G26 -> 4604 | E8: ='[1]Data Sheet'!H26 -> 5022 | F8: ='[1]Data Sheet'!I26 -> 4985 | G8: ='[1]Data Sheet'!J26 -> 5242
A9: Interest | B9: ='[1]Data Sheet'!E27 -> 924 | C9: ='[1]Data Sheet'!F27 -> 637 | D9: ='[1]Data Sheet'!G27 -> 784 | E9: ='[1]Data Sheet'!H27 -> 779 | F9: ='[1]Data Sheet'!I27 -> 778 | G9: ='[1]Data Sheet'!J27 -> 796
A10: Profit before tax | B10: ='[1]Data Sheet'!E28 -> 42248 | C10: ='[1]Data Sheet'!F28 -> 43760 | D10: ='[1]Data Sheet'!G28 -> 51687 | E10: ='[1]Data Sheet'!H28 -> 56907 | F10: ='[1]Data Sheet'!I28 -> 61997 | G10: ='[1]Data Sheet'!J28 -> 65331
A11: Tax | B11: ='[1]Data Sheet'!E29 -> 9801 | C11: ='[1]Data Sheet'!F29 -> 11198 | D11: ='[1]Data Sheet'!G29 -> 13238 | E11: ='[1]Data Sheet'!H29 -> 14604 | F11: ='[1]Data Sheet'!I29 -> 15898 | G11: ='[1]Data Sheet'!J29 -> 16534
A12: Net profit | B12: ='[1]Data Sheet'!E30 -> 32340 | C12: ='[1]Data Sheet'!F30 -> 32430 | D12: ='[1]Data Sheet'!G30 -> 38327 | E12: ='[1]Data Sheet'!H30 -> 42147 | F12: ='[1]Data Sheet'!I30 -> 45908 | G12: ='[1]Data Sheet'!J30 -> 48553
A13: EPS | B13: =IF('[1]Data Sheet'!E93>0,B12/'[1]Data Sheet'!E93,0) -> 86.184842 | C13: =IF('[1]Data Sheet'!F93>0,C12/'[1]Data Sheet'!F93,0) -> 87.669974 | D13: =IF('[1]Data Sheet'!G93>0,D12/'[1]Data Sheet'!G93,0) -> 104.74434 | E13: =IF('[1]Data Sheet'!H93>0,E12/'[1]Data Sheet'!H93,0) -> 115.18406 | F13: =IF('[1]Data Sheet'!I93>0,F12/'[1]Data Sheet'!I93,0) -> 126.88428 | G13: =IF('[1]Data Sheet'!J93>0,G12/'[1]Data Sheet'!J93,0) -> 134.19474
A14: Price to earning | B14: =IF(B15>0,B15/B13,"") -> 21.188181 | C14: =IF(C15>0,C15/C13,"") -> 36.247872 | D14: =IF(D15>0,D15/D13,"") -> 35.705511 | E14: =IF(E15>0,E15/E13,"") -> 27.832844 | F14: =IF(F15>0,F15/F13,"") -> 30.549885 | G14: =IF(G15>0,G15/G13,"") -> 26.872513
A15: Price | B15: ='[1]Data Sheet'!E90 -> 1826.1 | C15: ='[1]Data Sheet'!F90 -> 3177.85 | D15: ='[1]Data Sheet'!G90 -> 3739.95 | E15: ='[1]Data Sheet'!H90 -> 3205.9 | F15: ='[1]Data Sheet'!I90 -> 3876.3 | G15: ='[1]Data Sheet'!J90 -> 3606.15
A17: Narration | B17: 43891 | C17: 44256 | D17: 44621 | E17: 44986 | F17: 45352 | G17: 45717
A18: Equity Share Capital | B18: ='[1]Data Sheet'!E57 -> 375 | C18: 370 | D18: 366 | E18: 366 | F18: 362 | G18: 362
A19: Reserves | B19: ='[1]Data Sheet'!E58 -> 83751 | C19: 86063 | D19: 88773 | E19: 90058 | F19: 90127 | G19: 94394
A21: SHARE HOLDERS FUND(TOTAL EQUITY) | B21: =SUM(B18:B19) -> 84126 | C21: =SUM(C18:C19) -> 86433 | D21: =SUM(D18:D19) -> 89139 | E21: =SUM(E18:E19) -> 90424 | F21: =SUM(F18:F19) -> 90489 | G21: =SUM(G18:G19) -> 94756
A23: BORROWINGS | B23: ='[1]Data Sheet'!E59 -> 8174 | C23: 7795 | D23: 7818 | E23: 7688 | F23: 8021 | G23: 9392
A25: TOTAL ASSETS | B25: ='[1]Data Sheet'!E66 -> 120127 | C25: 129992 | D25: 140924 | E25: 142859 | F25: 145472 | G25: 158649
A27: CURRENT ASSETS | C27: 42908 | D27: 43969 | E27: 39200 | F27: 45580 | G27: 48585
A29: CURRENT LIABILITIES | C29: 35764 | D29: 43967 | E29: 44747 | F29: 46962 | G29: 54501
A31: Return on Equity(ROE) | C31: =C12/C21*100 -> 37.520392 | D31: =D12/D21*100 -> 42.996892 | E31: =E12/E21*100 -> 46.610413 | F31: =F12/F21*100 -> 50.733238 | G31: =G12/G21*100 -> 51.240027
A33: Return on Capital Employed(ROCE) | C33: =C6/(C25-C29)*100 -> 49.397207 | D33: =D6/(D25-D29)*100 -> 54.722196 | E33: =E6/(E25-E29)*100 -> 60.39934 | F33: =F6/(F25-F29)*100 -> 65.268501 | G33: =G6/(G25-G29)*100 -> 64.722318
A35: Net Profit Margin | C35: =C12/C4*100 -> 19.753071 | D35: =D12/D4*100 -> 19.987588 | E35: =E12/E4*100 -> 18.693947 | F35: =F12/F4*100 -> 19.057424 | G35: =G12/G4*100 -> 19.01623
A37: Asset Turnover | C37: =C4/C25 -> 1.2629777 | D37: =D4/D25 -> 1.3606909 | E37: =E4/E25 -> 1.5781855 | F37: =F4/F25 -> 1.6559407 | G37: =G4/G25 -> 1.6093641
A39: Debt/Equity | C39: =C23/C21 -> 0.090185462 | D39: =D23/D21 -> 0.087705718 | E39: =E23/E21 -> 0.085021676 | F39: =F23/F21 -> 0.088640608 | G39: =G23/G21 -> 0.099117734
A41: Interest Coverage | C41: =C6/C9 -> 73.070644 | D41: =D6/D9 -> 67.674745 | E41: =E6/E9 -> 76.070603 | F41: =F6/F9 -> 82.642674 | G41: =G6/G9 -> 84.682161
A43: Current Ratio | C43: =C27/C29 -> 1.1997539 | D43: =D27/D29 -> 1.0000455 | E43: =E27/E29 -> 0.87603638 | F43: =F27/F29 -> 0.97057195 | G43: =G27/G29 -> 0.89145153
A45: P/E Ratio | C45: =C15/C13 -> 36.247872 | D45: =D15/D13 -> 35.705511 | E45: =E15/E13 -> 27.832844 | F45: =F15/F13 -> 30.549885 | G45: =G15/G13 -> 26.872513
A47: EPS Growth | C47: =C13-B13/B13*100 -> -12.330026 | D47: =D13-C13/C13*100 -> 4.744336 | E47: =E13-D13/D13*100 -> 15.184062 | F47: =F13-E13/E13*100 -> 26.884276 | G47: =G13-F13/F13*100 -> 34.194743

Sheet visualization
A1: TCS Financial Ratio Dashboard | FY21–FY25
A3: Ratio | B3: FY21 | C3: FY22 | D3: FY23 | E3: FY24 | F3: FY25 | G3: Trend | H3: Insight
A4: ROE (%) | B4: ='raw data'!C31 -> 37.520392 | C4: ='raw data'!D31 -> 42.996892 | D4: ='raw data'!E31 -> 46.610413 | E4: ='raw data'!F31 -> 50.733238 | F4: ='raw data'!G31 -> 51.240027 | H4: ROE expanding — strong profitability
A5: ROCE (%) | B5: ='raw data'!C33 -> 49.397207 | C5: ='raw data'!D33 -> 54.722196 | D5: ='raw data'!E33 -> 60.39934 | E5: ='raw data'!F33 -> 65.268501 | F5: ='raw data'!G33 -> 64.722318 | H5: ROCE rising — efficient capital use
A6: Net Profit Margin (%) | B6: ='raw data'!C35 -> 19.753071 | C6: ='raw data'!D35 -> 19.987588 | D6: ='raw data'!E35 -> 18.693947 | E6: ='raw data'!F35 -> 19.057424 | F6: ='raw data'!G35 -> 19.01623 | H6: Stable ~19% margin
A7: Asset Turnover | B7: ='raw data'!C37 -> 1.2629777 | C7: ='raw data'!D37 -> 1.3606909 | D7: ='raw data'!E37 -> 1.5781855 | E7: ='raw data'!F37 -> 1.6559407 | F7: ='raw data'!G37 -> 1.6093641 | H7: Asset efficiency improving
A8: Debt/Equity | B8: ='raw data'!C39 -> 0.090185462 | C8: ='raw data'!D39 -> 0.087705718 | D8: ='raw data'!E39 -> 0.085021676 | E8: ='raw data'!F39 -> 0.088640608 | F8: ='raw data'!G39 -> 0.099117734 | H8: Near debt-free throughout
A9: Interest Coverage | B9: ='raw data'!C41 -> 73.070644 | C9: ='raw data'!D41 -> 67.674745 | D9: ='raw data'!E41 -> 76.070603 | E9: ='raw data'!F41 -> 82.642674 | F9: ='raw data'!G41 -> 84.682161 | H9: Interest coverage very strong
A10: Current Ratio | B10: ='raw data'!C43 -> 1.1997539 | C10: ='raw data'!D43 -> 1.0000455 | D10: ='raw data'!E43 -> 0.87603638 | E10: ='raw data'!F43 -> 0.97057195 | F10: ='raw data'!G43 -> 0.89145153 | H10: Liquidity tightening — watch
A11: P/E Ratio | B11: ='raw data'!C45 -> 36.247872 | C11: ='raw data'!D45 -> 35.705511 | D11: ='raw data'!E45 -> 27.832844 | E11: ='raw data'!F45 -> 30.549885 | F11: ='raw data'!G45 -> 26.872513 | H11: Valuation compressing
A12: EPS Growth (%) | C12: ='raw data'!D47 -> 4.744336 | D12: ='raw data'!E47 -> 15.184062 | E12: ='raw data'!F47 -> 26.884276 | F12: ='raw data'!G47 -> 34.194743 | H12: EPS growth accelerating
